README.md
setup.py
alibabacloud_ros20150901/__init__.py
alibabacloud_ros20150901/client.py
alibabacloud_ros20150901/models.py
alibabacloud_ros20150901.egg-info/PKG-INFO
alibabacloud_ros20150901.egg-info/SOURCES.txt
alibabacloud_ros20150901.egg-info/dependency_links.txt
alibabacloud_ros20150901.egg-info/requires.txt
alibabacloud_ros20150901.egg-info/top_level.txt